MANIFEST.in
README.rst
setup.py
markmywords/__init__.py
markmywords/markov.py
markmywords.egg-info/PKG-INFO
markmywords.egg-info/SOURCES.txt
markmywords.egg-info/dependency_links.txt
markmywords.egg-info/not-zip-safe
markmywords.egg-info/top_level.txt