Metadata-Version: 1.1
Name: markmywords
Version: 0.2
Summary: A text-generating Markov chain library
Home-page: http://github.com/useanalias/markmywords
Author: useanalias
Author-email: use.an.alias@gmail.com
License: MIT
Keywords: markov chain artificial intelligence text generation
Platform: UNKNOWN
Classifier: Development Status :: 1 - Planning
Classifier: Intended Audience :: Developers
Classifier: License :: OSI Approved :: MIT License
Classifier: Operating System :: OS Independent
Classifier: Programming Language :: Python
Classifier: Programming Language :: Python :: 3.5
Classifier: Topic :: Scientific/Engineering :: Artificial Intelligence
Classifier: Topic :: Software Development :: Libraries
